setup.py
gislite/__init__.py
gislite/const.py
gislite/helper.py
gislite/layer_builder.py
gislite/site_builder.py
gislite/sphinx_builder.py
gislite/tile_builder.py
gislite.egg-info/PKG-INFO
gislite.egg-info/SOURCES.txt
gislite.egg-info/dependency_links.txt
gislite.egg-info/requires.txt
gislite.egg-info/top_level.txt
gislite.egg-info/zip-safe