Metadata-Version: 1.1
Name: gislite
Version: 0.0.4
Summary: Static site generator (SSG) for GIS data publishment as light WebGIS application.
Home-page: http://gislite.osgeo.cn
Author: bukun
Author-email: bukun@osgeo.cn
License: MIT License
Keywords: WebGIS,Static site generator
Platform: any
Classifier: Development Status :: 3 - Alpha
Classifier: Intended Audience :: Developers
Classifier: Topic :: Software Development :: Libraries :: Python Modules
Classifier: License :: OSI Approved :: MIT License
Classifier: Programming Language :: Python :: 3
Classifier: Programming Language :: Python :: 3.7
